src/__init__.py
src/main.py
src/_internal/__init__.py
src/_internal/archiver/__init__.py
src/_internal/archiver/archiver.py
src/_internal/telethon_/__init__.py
src/_internal/telethon_/dialog.py
src/_internal/telethon_/dialogsource.py
tests/__init__.py
tests/test_archiver.py
tests/mocks/__init__.py
tests/mocks/dialog/__init__.py
tests/mocks/dialog/dialog.py
tests/mocks/dialogsource/__init__.py
tests/mocks/dialogsource/dialogsource.py
dk.charon-0.1.dist-info/LICENSE
dk.charon-0.1.dist-info/LICENSE.txt
dk.charon-0.1.dist-info/METADATA
dk.charon-0.1.dist-info/WHEEL
dk.charon-0.1.dist-info/entry_points.txt
dk.charon-0.1.dist-info/top_level.txt
dk.charon-0.1.dist-info/RECORD
