Metadata-Version: 2.1
Name: dk.charon
Version: 0.1
Summary: Tool for managing telegram chats
Home-page: https://github.com/madetara/charon
Author: Danil Kabanov
Author-email: madetara@yandex.com
License: UNKNOWN
Platform: UNKNOWN
Classifier: Development Status :: 4 - Beta
Classifier: License :: OSI Approved :: GNU General Public License v3 (GPLv3)
Classifier: Environment :: Console
Classifier: Operating System :: OS Independent
Classifier: Programming Language :: Python :: 3.7
Classifier: Topic :: Utilities
Requires-Dist: telethon
Requires-Dist: click
